[
  {
    "id": "83fb0ed3-b359-4e0b-b073-a306f77b497a",
    "ten_khach_hang": "NGUYỄN TRIỆU ĐỨC HUY",
    "so_don_hang": "N31920-VSO-26-03-0435",
    "dong_xe": "VF 3",
    "phien_ban": "Plus",
    "ngoai_that": "Zenith Grey (CE1V)",
    "noi_that": "Black",
    "tvbh": "NGUYỄN THỊ YẾN VY",
    "vin": "RLNVBL9K3TT710550",
    "so_may": "TZ160X30G26010300004",
    "ngay_yeu_cau": "2026-04-03T02:52:08.407+00:00",
    "ngay_xuat_hoa_don": "2026-04-06T06:21:37.085674+00:00",
    "hoa_hong_ung": "9000000",
    "vpoint": "0",
    "chinh_sach": "Chương trình Mãnh liệt vì tương lai xanh - Trừ vào giá (6%), Chương trình tặng Voucher giờ Trái Đất - 5Tr",
    "ngay_coc": "2026-05-26",
    "ket_qua_gui_mail": "",
    "url_hop_dong": "https://drive.google.com/file/d/15s__JrA7bwHdyH14xvUCQdeZB27AskVF/preview",
    "url_de_nghi_xhd": "https://drive.google.com/file/d/1cvkq-4ORJVzP8dUn6F2PBqdjpEAOzd0N/preview",
    "url_hoa_don_da_xuat": "https://drive.google.com/file/d/164EfEbY2YMq4FcELedzvXsfMCYhE5-dL/preview",
    "trang_thai_vc": "Chờ ký hóa đơn",
    "ghi_chu_admin": "Bổ sung phụ lục",
    "created_at": "2026-04-03T02:52:13.418468+00:00",
    "ghi_chu_ai": "✅ Khớp 100% chứng từ, không phát hiện sai lệch.",
    "thoi_gian_can_xe": null
  },
  {
    "id": "f5c6e8cc-e621-4f11-a355-16033730e5e1",
    "ten_khach_hang": "NGUYỄN VĂN KHÔI",
    "so_don_hang": "N31913-VSO-26-04-0008",
    "dong_xe": "VF 5",
    "phien_ban": "Plus",
    "ngoai_that": "Brahminy White (CE18)",
    "noi_that": "Black",
    "tvbh": "PHẠM THỊ THÚY NGA",
    "vin": "RLNV5JSE8TH731574",
    "so_may": "VFCAFB263100100",
    "ngay_yeu_cau": "2026-04-07T08:33:19.988+00:00",
    "ngay_xuat_hoa_don": null,
    "hoa_hong_ung": "14000000",
    "vpoint": "50000",
    "chinh_sach": "Chương trình Mãnh liệt vì tương lai xanh - Trừ vào giá (6%)",
    "ngay_coc": "2026-04-03",
    "ket_qua_gui_mail": "",
    "url_hop_dong": "https://drive.google.com/file/d/1ZuAf25kP6_En9fcLgBLG2cxs5FOk0VWd/preview",
    "url_de_nghi_xhd": "https://drive.google.com/file/d/1xcK8klM47KR6nRwalDtu6Cf7_Tfzu2Bg/preview",
    "url_hoa_don_da_xuat": "",
    "trang_thai_vc": "Đã phê duyệt",
    "ghi_chu_admin": "",
    "created_at": "2026-04-07T08:33:22.278813+00:00",
    "ghi_chu_ai": "",
    "thoi_gian_can_xe": null
  },
  {
    "id": "dd6a2e23-0c43-4e8e-9fb9-d7d8f7241009",
    "ten_khach_hang": "NGUYỄN TRẦN ANH THƯ",
    "so_don_hang": "N31913-VSO-26-03-0453",
    "dong_xe": "VF 6",
    "phien_ban": "Plus Tiêu chuẩn 2",
    "ngoai_that": "Jet Black (CE11)",
    "noi_that": "Brown",
    "tvbh": "NGUYỄN DƯ THUẬN",
    "vin": "RLLVAG8C8TH740871",
    "so_may": "",
    "ngay_yeu_cau": "2026-04-07T10:08:42.959+00:00",
    "ngay_xuat_hoa_don": null,
    "hoa_hong_ung": "18000000",
    "vpoint": "0",
    "chinh_sach": "Chương trình Mãnh liệt vì tương lai xanh - Trừ vào giá (6%), Chương trình tặng Voucher giờ Trái Đất - 10Tr",
    "ngay_coc": "2026-03-19",
    "ket_qua_gui_mail": "",
    "url_hop_dong": "https://jwvgxqrkjlbewvpkvucj.supabase.co/storage/v1/object/public/yeucauxhd-files/N31913-VSO-26-03-0453/HDMB_NGUYEN_TRAN_ANH_THU_1775556522959.pdf",
    "url_de_nghi_xhd": "https://jwvgxqrkjlbewvpkvucj.supabase.co/storage/v1/object/public/yeucauxhd-files/N31913-VSO-26-03-0453/DNXHD_NGUYEN_TRAN_ANH_THU_1775556522959.pdf",
    "url_hoa_don_da_xuat": "",
    "trang_thai_vc": "",
    "ghi_chu_admin": "",
    "created_at": "2026-04-07T10:08:47.912753+00:00",
    "ghi_chu_ai": "",
    "thoi_gian_can_xe": null
  },
  {
    "id": "d45e976a-f70d-4c56-a71d-1bdf40aef9d3",
    "ten_khach_hang": "HOÀNG VĂN CƯỜNG",
    "so_don_hang": "N31913-VSO-26-03-0346",
    "dong_xe": "LIMO",
    "phien_ban": "LIMO",
    "ngoai_that": "Jet Black (CE11)",
    "noi_that": "Black",
    "tvbh": "PHẠM TRỌNG HUY",
    "vin": "RLLVFPNTXTH707862",
    "so_may": "ENBALB25C080202",
    "ngay_yeu_cau": "2026-03-04T11:50:20+00:00",
    "ngay_xuat_hoa_don": "2026-06-04T00:00:00+00:00",
    "hoa_hong_ung": "12.000.000",
    "vpoint": "0",
    "chinh_sach": "Chương trình Mãnh liệt vì tương lai xanh - Trừ vào giá (6%), Chương trình tặng Voucher giờ Trái Đất - 10Tr",
    "ngay_coc": "24/03/2026",
    "ket_qua_gui_mail": "",
    "url_hop_dong": "Tải File",
    "url_de_nghi_xhd": "Tải File",
    "url_hoa_don_da_xuat": "Tải File",
    "trang_thai_vc": "",
    "ghi_chu_admin": "",
    "created_at": "2026-04-07T17:10:13.723942+00:00",
    "ghi_chu_ai": "",
    "thoi_gian_can_xe": null
  },
  {
    "id": "2a2d018d-cfd0-4cf0-b960-a2dfc0b888d4",
    "ten_khach_hang": "LƯU THỊ LỆ HÀ",
    "so_don_hang": "N31913-VSO-26-03-0463",
    "dong_xe": "VF 3",
    "phien_ban": "Base Tiêu chuẩn 2",
    "ngoai_that": "Zenith Grey (CE1V)",
    "noi_that": "Black",
    "tvbh": "TỐNG THÀNH ĐẠT",
    "vin": "RLNVBL9K6TT706928",
    "so_may": "TZ160X30G25122300093",
    "ngay_yeu_cau": "2026-06-04T09:18:47+00:00",
    "ngay_xuat_hoa_don": "2026-06-04T00:00:00+00:00",
    "hoa_hong_ung": "13.000.000",
    "vpoint": "0",
    "chinh_sach": "Chương trình Mãnh liệt vì tương lai xanh - Trừ vào giá (6%), Chương trình tặng Voucher giờ Trái Đất - 5Tr",
    "ngay_coc": "28/03/2026",
    "ket_qua_gui_mail": "",
    "url_hop_dong": "Tải File",
    "url_de_nghi_xhd": "https://drive.google.com/file/d/1AfbVbGeO_oCA2Clo842HRwjYw23Se2MU/preview",
    "url_hoa_don_da_xuat": "Tải File",
    "trang_thai_vc": "",
    "ghi_chu_admin": "",
    "created_at": "2026-04-07T17:10:13.723967+00:00",
    "ghi_chu_ai": "",
    "thoi_gian_can_xe": null
  },
  {
    "id": "e00d9e2b-1245-416c-80d8-677c070fcc38",
    "ten_khach_hang": "NGUYỄN ĐÌNH ĐIỆP",
    "so_don_hang": "N31913-VSO-26-03-0485",
    "dong_xe": "VF 5",
    "phien_ban": "Plus",
    "ngoai_that": "Crimson Red (CE1M)",
    "noi_that": "Black",
    "tvbh": "NGUYỄN THIỆN THẢO",
    "vin": "RLNV5JSE7TH739455",
    "so_may": "VFCAFB263280021",
    "ngay_yeu_cau": "2026-07-04T09:36:33+00:00",
    "ngay_xuat_hoa_don": null,
    "hoa_hong_ung": "10.000.000",
    "vpoint": "0",
    "chinh_sach": "Chương trình Mãnh liệt vì tương lai xanh - Trừ vào giá (6%), Chương trình tặng Voucher giờ Trái Đất - 7Tr",
    "ngay_coc": "29/05/2026",
    "ket_qua_gui_mail": "",
    "url_hop_dong": "https://drive.google.com/file/d/1XBAmXb9o80SKTSFPa1QP70virtoevRuM/preview",
    "url_de_nghi_xhd": "https://drive.google.com/file/d/1jJQLveZxr4SGtsVPH6n-B1ukc01-eKLd/preview",
    "url_hoa_don_da_xuat": null,
    "trang_thai_vc": "",
    "ghi_chu_admin": "",
    "created_at": "2026-04-07T17:10:13.723966+00:00",
    "ghi_chu_ai": "",
    "thoi_gian_can_xe": null
  },
  {
    "id": "6dd792e1-2295-448b-bd87-f366264a45a0",
    "ten_khach_hang": "NGÔ VĂN QUÝ",
    "so_don_hang": "N31913-VSO-26-04-0016",
    "dong_xe": "VF 5",
    "phien_ban": "Plus",
    "ngoai_that": "Urbant Mint (CE1W)",
    "noi_that": "Black",
    "tvbh": "PHAN VĂN CƯỜNG",
    "vin": "RLNV5JSE5TH715283",
    "so_may": "VFCAFB261180132",
    "ngay_yeu_cau": "2026-04-08T04:26:51.298+00:00",
    "ngay_xuat_hoa_don": null,
    "hoa_hong_ung": "14000000",
    "vpoint": "0",
    "chinh_sach": "Chương trình Mãnh liệt vì tương lai xanh - Trừ vào giá (6%)",
    "ngay_coc": "2026-04-05",
    "ket_qua_gui_mail": "",
    "url_hop_dong": "https://drive.google.com/file/d/1fA-dN9bK2TtQazmFHqZbtadp0PNEGxls/preview",
    "url_de_nghi_xhd": "https://drive.google.com/file/d/1E6Mqie41V0nS1-HPXaFogY7aa5B7-iIV/preview",
    "url_hoa_don_da_xuat": "",
    "trang_thai_vc": "",
    "ghi_chu_admin": "",
    "created_at": "2026-04-08T04:26:56.415979+00:00",
    "ghi_chu_ai": "✅ Khớp 100% chứng từ, không phát hiện sai lệch.",
    "thoi_gian_can_xe": null
  },
  {
    "id": "5bf229bb-307e-499d-a769-d1ba1406324c",
    "ten_khach_hang": "TRẦN THỊ VIỆT TRINH",
    "so_don_hang": "N31920-VSO-26-03-0291",
    "dong_xe": "VF 7",
    "phien_ban": "Plus_Metal Tiêu chuẩn 2 (1 Cầu)",
    "ngoai_that": "Brahminy White (CE18)",
    "noi_that": "Brown",
    "tvbh": "THÀNH NGỌC VINH",
    "vin": "RLLV3FKCXTH733210",
    "so_may": "VFBALB262070022",
    "ngay_yeu_cau": "2026-04-04T05:27:36.465+00:00",
    "ngay_xuat_hoa_don": "2026-04-06T06:59:38.014691+00:00",
    "hoa_hong_ung": "15000000",
    "vpoint": "0",
    "chinh_sach": "Chương trình Mãnh liệt vì tương lai xanh - Trừ vào giá (6%), Chương trình tặng Voucher giờ Trái Đất - 15Tr",
    "ngay_coc": "2026-03-23",
    "ket_qua_gui_mail": "",
    "url_hop_dong": "https://drive.google.com/file/d/1ZMSE4UGtK0fvQr5Mji694kIUtunrt0h6/preview",
    "url_de_nghi_xhd": "https://drive.google.com/file/d/1oBfu1Tcm3Il3uvgL8k44JV1GaBeI693F/preview",
    "url_hoa_don_da_xuat": "https://drive.google.com/file/d/1asNcicYFoSqoHzC31brlIBVj5VSLe3ae/preview",
    "trang_thai_vc": "Chờ ký hóa đơn",
    "ghi_chu_admin": "",
    "created_at": "2026-04-04T05:27:36.912174+00:00",
    "ghi_chu_ai": "✅ Khớp 100% chứng từ, không phát hiện sai lệch.",
    "thoi_gian_can_xe": null
  },
  {
    "id": "88d0ad78-3c20-4baf-9d6d-52ca3e24d338",
    "ten_khach_hang": "NGUYỄN VĂN THÁI",
    "so_don_hang": "N31911-VSO-26-04-0001",
    "dong_xe": "VF 5",
    "phien_ban": "Plus",
    "ngoai_that": "Brahminy White (CE18)",
    "noi_that": "Black",
    "tvbh": "NGUYỄN BẢO XUYÊN",
    "vin": "RLNV5JSE7TH710618",
    "so_may": "VFCAFB261180141",
    "ngay_yeu_cau": "2026-04-06T07:16:34.335+00:00",
    "ngay_xuat_hoa_don": "2026-04-06T08:29:52.892592+00:00",
    "hoa_hong_ung": "10000000",
    "vpoint": "0",
    "chinh_sach": "Chương trình Mãnh liệt vì tương lai xanh - Trừ vào giá (6%)",
    "ngay_coc": "2026-03-28",
    "ket_qua_gui_mail": "",
    "url_hop_dong": "https://drive.google.com/file/d/16w-toW3nMal-NJmUJpw9F6ps_I6zZHNI/preview",
    "url_de_nghi_xhd": "https://drive.google.com/file/d/1WmnIgzheefi_qyGltxqfqmqAycmhj8v-/preview",
    "url_hoa_don_da_xuat": "https://drive.google.com/file/d/1zXRH5TOO6CFtm7sUD76ILagWbLSTQP2c/preview",
    "trang_thai_vc": "Chờ ký hóa đơn",
    "ghi_chu_admin": "",
    "created_at": "2026-04-06T07:16:35.177943+00:00",
    "ghi_chu_ai": "✅ Khớp 100% chứng từ, không phát hiện sai lệch.",
    "thoi_gian_can_xe": null
  }
]